README.txt
setup.cfg
setup.py
django_cenvars/__info__.py
django_cenvars/__init__.py
django_cenvars/admin.py
django_cenvars/settings.py
django_cenvars/signals.py
django_cenvars/urls.py
django_cenvars.egg-info/PKG-INFO
django_cenvars.egg-info/SOURCES.txt
django_cenvars.egg-info/dependency_links.txt
django_cenvars.egg-info/requires.txt
django_cenvars.egg-info/top_level.txt
django_cenvars/management/__init__.py
django_cenvars/management/commands/__init__.py
django_cenvars/management/commands/cenvars_newkey.py
django_cenvars/migrations/0001_initial.py
django_cenvars/migrations/0002_auto_multiple_inheritance.py
django_cenvars/migrations/0003_auto_add_sortorder.py
django_cenvars/migrations/__init__.py
django_cenvars/models/__init__.py
django_cenvars/tests/__init__.py
django_cenvars/tests/test_main.py
django_cenvars/tools/__init__.py
django_cenvars/tools/models.py
django_cenvars/tools/sanitize.py
django_cenvars/views/__init__.py
interface/__init__.py
interface/settings.py
interface/urls.py
interface/wsgi.py