Metadata-Version: 1.1
Name: django-cenvars
Version: 0.0.1.2
Summary: Django Centralised Environment Variables Service
Home-page: https://bitbucket.org/hellwig/django-cenvars/
Author: Martin P. Hellwig
Author-email: martin.hellwig@gmail.com
License: BSD
Download-URL: https://bitbucket.org/hellwig/django-cenvars/download/0.0.1.2.zip
Keywords: django,django-integrator
Platform: UNKNOWN
Classifier: Programming Language :: Python :: 3
